file_helper_utils/__init__.py
file_helper_utils/console_helper.py
file_helper_utils/utils.py
file_helper_utils-0.1.0.dist-info/AUTHORS.rst
file_helper_utils-0.1.0.dist-info/METADATA
file_helper_utils-0.1.0.dist-info/WHEEL
file_helper_utils-0.1.0.dist-info/entry_points.txt
file_helper_utils-0.1.0.dist-info/top_level.txt
file_helper_utils-0.1.0.dist-info/RECORD
